lockdowndates/__init__.py
lockdowndates/_nbdev.py
lockdowndates/core.py
lockdowndates/index.py
lockdowndates-0.0.4.dist-info/LICENSE
lockdowndates-0.0.4.dist-info/METADATA
lockdowndates-0.0.4.dist-info/WHEEL
lockdowndates-0.0.4.dist-info/top_level.txt
lockdowndates-0.0.4.dist-info/RECORD
