Metadata-Version: 2.1
Name: lockdowndates
Version: 0.0.4
Summary: Retrieve the dates of the restrictions in countries imposed by governments around the world during the covid-19 pandemic.
Home-page: https://github.com/seanyboi/lockdowndates/tree/main/
Author: Sean O'Connor
Author-email: oconnorjamessean@gmail.com
License: Apache Software License 2.0
Keywords: lockdown,covid,pandemic,coronavirus,timeseries,machinelearning,nbdev,fastai,restrictions,python,pandas
Platform: UNKNOWN
Classifier: Development Status :: 3 - Alpha
Classifier: Intended Audience :: Developers
Classifier: Natural Language :: English
Classifier: Programming Language :: Python :: 3.8
Classifier: License :: OSI Approved :: Apache Software License
Requires-Python: >=3.8
License-File: LICENSE
Requires-Dist: pip
Requires-Dist: packaging
Requires-Dist: pandas (==1.4.0)
Requires-Dist: pyarrow
Provides-Extra: dev
